setup.py
ab_resbase/__init__.py
ab_resbase.egg-info/PKG-INFO
ab_resbase.egg-info/SOURCES.txt
ab_resbase.egg-info/dependency_links.txt
ab_resbase.egg-info/not-zip-safe
ab_resbase.egg-info/top_level.txt