Metadata-Version: 1.0
Name: ab-resbase
Version: 0.4
Summary: clinical trial information retriver
Home-page: http://github.com/tongling/ab_resbase
Author: Ling
Author-email: an520999@gmail.com
License: MIT
Platform: UNKNOWN
